[
    {
        "Longitude": -77.01065,
        "Latitude": -12.13001
    },
    {
        "Longitude": -77.01065,
        "Latitude": -12.12995
    },
    {
        "Longitude": -77.01065,
        "Latitude": -12.12994
    },
    {
        "Longitude": -77.01072,
        "Latitude": -12.1294
    },
    {
        "Longitude": -77.01074,
        "Latitude": -12.1292
    },
    {
        "Longitude": -77.01076,
        "Latitude": -12.12899
    },
    {
        "Longitude": -77.01076,
        "Latitude": -12.12887
    },
    {
        "Longitude": -77.01076,
        "Latitude": -12.12878
    },
    {
        "Longitude": -77.01075,
        "Latitude": -12.12869
    },
    {
        "Longitude": -77.01074,
        "Latitude": -12.12866
    },
    {
        "Longitude": -77.01071,
        "Latitude": -12.12842
    },
    {
        "Longitude": -77.01069,
        "Latitude": -12.12833
    },
    {
        "Longitude": -77.01068,
        "Latitude": -12.12812
    },
    {
        "Longitude": -77.01037,
        "Latitude": -12.12816
    },
    {
        "Longitude": -77.01003,
        "Latitude": -12.12822
    },
    {
        "Longitude": -77.00987,
        "Latitude": -12.12824
    },
    {
        "Longitude": -77.00986,
        "Latitude": -12.12825
    },
    {
        "Longitude": -77.00969,
        "Latitude": -12.12827
    },
    {
        "Longitude": -77.00965,
        "Latitude": -12.12864
    },
    {
        "Longitude": -77.00964,
        "Latitude": -12.1287
    },
    {
        "Longitude": -77.00983,
        "Latitude": -12.1287
    },
    {
        "Longitude": -77.00985,
        "Latitude": -12.1287
    },
    {
        "Longitude": -77.01001,
        "Latitude": -12.12869
    },
    {
        "Longitude": -77.01002,
        "Latitude": -12.12869
    },
    {
        "Longitude": -77.01037,
        "Latitude": -12.12868
    },
    {
        "Longitude": -77.01075,
        "Latitude": -12.12869
    },
    {
        "Longitude": -77.01082,
        "Latitude": -12.12868
    },
    {
        "Longitude": -77.01097,
        "Latitude": -12.12867
    },
    {
        "Longitude": -77.01137,
        "Latitude": -12.12865
    },
    {
        "Longitude": -77.01159,
        "Latitude": -12.12864
    },
    {
        "Longitude": -77.01177,
        "Latitude": -12.12867
    },
    {
        "Longitude": -77.01197,
        "Latitude": -12.12874
    },
    {
        "Longitude": -77.01237,
        "Latitude": -12.12889
    },
    {
        "Longitude": -77.01253,
        "Latitude": -12.12895
    },
    {
        "Longitude": -77.01279,
        "Latitude": -12.12904
    },
    {
        "Longitude": -77.01299,
        "Latitude": -12.12911
    },
    {
        "Longitude": -77.01315,
        "Latitude": -12.12918
    },
    {
        "Longitude": -77.01357,
        "Latitude": -12.12934
    },
    {
        "Longitude": -77.0136,
        "Latitude": -12.12935
    },
    {
        "Longitude": -77.01367,
        "Latitude": -12.12939
    },
    {
        "Longitude": -77.01361,
        "Latitude": -12.12953
    },
    {
        "Longitude": -77.01355,
        "Latitude": -12.12973
    },
    {
        "Longitude": -77.01348,
        "Latitude": -12.12997
    },
    {
        "Longitude": -77.01327,
        "Latitude": -12.12991
    },
    {
        "Longitude": -77.01322,
        "Latitude": -12.12989
    },
    {
        "Longitude": -77.01312,
        "Latitude": -12.12985
    },
    {
        "Longitude": -77.01238,
        "Latitude": -12.12956
    },
    {
        "Longitude": -77.01225,
        "Latitude": -12.1295
    },
    {
        "Longitude": -77.01191,
        "Latitude": -12.12937
    },
    {
        "Longitude": -77.01174,
        "Latitude": -12.12932
    },
    {
        "Longitude": -77.01167,
        "Latitude": -12.1293
    },
    {
        "Longitude": -77.01166,
        "Latitude": -12.12949
    },
    {
        "Longitude": -77.01166,
        "Latitude": -12.1295
    },
    {
        "Longitude": -77.01167,
        "Latitude": -12.12959
    },
    {
        "Longitude": -77.01172,
        "Latitude": -12.12993
    },
    {
        "Longitude": -77.01174,
        "Latitude": -12.12999
    },
    {
        "Longitude": -77.01186,
        "Latitude": -12.1305
    },
    {
        "Longitude": -77.01245,
        "Latitude": -12.13037
    },
    {
        "Longitude": -77.01246,
        "Latitude": -12.13043
    },
    {
        "Longitude": -77.01247,
        "Latitude": -12.1305
    },
    {
        "Longitude": -77.01248,
        "Latitude": -12.13057
    },
    {
        "Longitude": -77.01249,
        "Latitude": -12.13061
    },
    {
        "Longitude": -77.01251,
        "Latitude": -12.13066
    },
    {
        "Longitude": -77.01253,
        "Latitude": -12.13073
    },
    {
        "Longitude": -77.01255,
        "Latitude": -12.13078
    },
    {
        "Longitude": -77.01256,
        "Latitude": -12.13079
    },
    {
        "Longitude": -77.01261,
        "Latitude": -12.13088
    },
    {
        "Longitude": -77.01263,
        "Latitude": -12.13092
    },
    {
        "Longitude": -77.01265,
        "Latitude": -12.13093
    },
    {
        "Longitude": -77.01275,
        "Latitude": -12.13105
    },
    {
        "Longitude": -77.01277,
        "Latitude": -12.13107
    },
    {
        "Longitude": -77.01289,
        "Latitude": -12.1312
    },
    {
        "Longitude": -77.01291,
        "Latitude": -12.13118
    },
    {
        "Longitude": -77.01305,
        "Latitude": -12.13108
    },
    {
        "Longitude": -77.01308,
        "Latitude": -12.13104
    },
    {
        "Longitude": -77.01311,
        "Latitude": -12.131
    },
    {
        "Longitude": -77.01313,
        "Latitude": -12.13094
    },
    {
        "Longitude": -77.01314,
        "Latitude": -12.13085
    },
    {
        "Longitude": -77.01314,
        "Latitude": -12.13077
    },
    {
        "Longitude": -77.01313,
        "Latitude": -12.13073
    },
    {
        "Longitude": -77.01313,
        "Latitude": -12.13072
    },
    {
        "Longitude": -77.0131,
        "Latitude": -12.13056
    },
    {
        "Longitude": -77.0131,
        "Latitude": -12.13055
    },
    {
        "Longitude": -77.01307,
        "Latitude": -12.13037
    },
    {
        "Longitude": -77.01304,
        "Latitude": -12.13022
    },
    {
        "Longitude": -77.01304,
        "Latitude": -12.1301
    },
    {
        "Longitude": -77.01305,
        "Latitude": -12.13005
    },
    {
        "Longitude": -77.01306,
        "Latitude": -12.12999
    },
    {
        "Longitude": -77.01308,
        "Latitude": -12.12995
    },
    {
        "Longitude": -77.01309,
        "Latitude": -12.12991
    },
    {
        "Longitude": -77.01312,
        "Latitude": -12.12985
    },
    {
        "Longitude": -77.01238,
        "Latitude": -12.12956
    },
    {
        "Longitude": -77.01225,
        "Latitude": -12.1295
    },
    {
        "Longitude": -77.01191,
        "Latitude": -12.12937
    },
    {
        "Longitude": -77.01174,
        "Latitude": -12.12932
    },
    {
        "Longitude": -77.01167,
        "Latitude": -12.1293
    },
    {
        "Longitude": -77.01163,
        "Latitude": -12.12929
    },
    {
        "Longitude": -77.01152,
        "Latitude": -12.12927
    },
    {
        "Longitude": -77.01144,
        "Latitude": -12.12925
    },
    {
        "Longitude": -77.01121,
        "Latitude": -12.12922
    },
    {
        "Longitude": -77.01094,
        "Latitude": -12.1292
    },
    {
        "Longitude": -77.01076,
        "Latitude": -12.1292
    },
    {
        "Longitude": -77.01074,
        "Latitude": -12.1292
    },
    {
        "Longitude": -77.01076,
        "Latitude": -12.12899
    },
    {
        "Longitude": -77.01076,
        "Latitude": -12.12887
    },
    {
        "Longitude": -77.01076,
        "Latitude": -12.12878
    },
    {
        "Longitude": -77.01075,
        "Latitude": -12.12869
    },
    {
        "Longitude": -77.01082,
        "Latitude": -12.12868
    },
    {
        "Longitude": -77.01097,
        "Latitude": -12.12867
    },
    {
        "Longitude": -77.01137,
        "Latitude": -12.12865
    },
    {
        "Longitude": -77.01159,
        "Latitude": -12.12864
    },
    {
        "Longitude": -77.01177,
        "Latitude": -12.12867
    },
    {
        "Longitude": -77.01197,
        "Latitude": -12.12874
    },
    {
        "Longitude": -77.01237,
        "Latitude": -12.12889
    },
    {
        "Longitude": -77.01253,
        "Latitude": -12.12895
    },
    {
        "Longitude": -77.01279,
        "Latitude": -12.12904
    },
    {
        "Longitude": -77.01299,
        "Latitude": -12.12911
    },
    {
        "Longitude": -77.013,
        "Latitude": -12.12909
    },
    {
        "Longitude": -77.01306,
        "Latitude": -12.12894
    },
    {
        "Longitude": -77.01312,
        "Latitude": -12.1288
    },
    {
        "Longitude": -77.01315,
        "Latitude": -12.12872
    },
    {
        "Longitude": -77.01318,
        "Latitude": -12.12864
    },
    {
        "Longitude": -77.01319,
        "Latitude": -12.12857
    },
    {
        "Longitude": -77.01319,
        "Latitude": -12.12849
    },
    {
        "Longitude": -77.01319,
        "Latitude": -12.12838
    },
    {
        "Longitude": -77.01319,
        "Latitude": -12.12817
    },
    {
        "Longitude": -77.01313,
        "Latitude": -12.12782
    },
    {
        "Longitude": -77.01295,
        "Latitude": -12.12785
    },
    {
        "Longitude": -77.01276,
        "Latitude": -12.12787
    },
    {
        "Longitude": -77.01258,
        "Latitude": -12.1279
    },
    {
        "Longitude": -77.01239,
        "Latitude": -12.12793
    },
    {
        "Longitude": -77.01221,
        "Latitude": -12.12796
    },
    {
        "Longitude": -77.01203,
        "Latitude": -12.12798
    },
    {
        "Longitude": -77.01184,
        "Latitude": -12.12801
    },
    {
        "Longitude": -77.01167,
        "Latitude": -12.12804
    },
    {
        "Longitude": -77.01166,
        "Latitude": -12.12828
    },
    {
        "Longitude": -77.01166,
        "Latitude": -12.1283
    },
    {
        "Longitude": -77.01159,
        "Latitude": -12.12864
    },
    {
        "Longitude": -77.01177,
        "Latitude": -12.12867
    },
    {
        "Longitude": -77.01197,
        "Latitude": -12.12874
    },
    {
        "Longitude": -77.01237,
        "Latitude": -12.12889
    },
    {
        "Longitude": -77.01253,
        "Latitude": -12.12895
    },
    {
        "Longitude": -77.01279,
        "Latitude": -12.12904
    },
    {
        "Longitude": -77.01299,
        "Latitude": -12.12911
    },
    {
        "Longitude": -77.01315,
        "Latitude": -12.12918
    },
    {
        "Longitude": -77.01357,
        "Latitude": -12.12934
    },
    {
        "Longitude": -77.0136,
        "Latitude": -12.12935
    },
    {
        "Longitude": -77.01367,
        "Latitude": -12.12939
    },
    {
        "Longitude": -77.01377,
        "Latitude": -12.12944
    },
    {
        "Longitude": -77.01382,
        "Latitude": -12.12946
    },
    {
        "Longitude": -77.01419,
        "Latitude": -12.12952
    },
    {
        "Longitude": -77.01435,
        "Latitude": -12.12954
    },
    {
        "Longitude": -77.01465,
        "Latitude": -12.12957
    }
]